<?xml version="1.0" encoding="utf-8"?>
<ROOT>
   <points>[0 0 0; 0.0309016994374947 0.0951056516295154 0; 0.050447856188097 0.155262536475891 0; 0.0671982616963462 0.206814983749639 0; 0.082357483255013 0.25347027037714 0; 0.0964336919536974 0.296792386154924 0; -0.0809016994374947 0.0587785252292473 0; -0.132074202160005 0.0959575247216209 0; -0.175927333105945 0.127818689340034 0; -0.215614690389524 0.156653242230698 0; -0.252466683195417 0.183427782245927 0; -0.0809016994374948 -0.0587785252292473 0; -0.132074202160005 -0.0959575247216208 0; -0.175927333105945 -0.127818689340034 0; -0.215614690389524 -0.156653242230698 0; -0.252466683195417 -0.183427782245927 0; 0.0309016994374947 -0.0951056516295154 0; 0.050447856188097 -0.155262536475891 0; 0.0671982616963462 -0.206814983749639 0; 0.0823574832550129 -0.25347027037714 0; 0.0964336919536973 -0.296792386154924 0; 0.1 -2.44929359829471e-017 0; 0.163252691943815 -3.99853773282365e-017 0; 0.217458142819197 -5.32618837104114e-017 0; 0.266514414269023 -6.5277204872238e-017 0; 0.312065982483439 -7.64341213142236e-017 0]</points>
   <factor>[1; 1; 1; 1; 1; 1; 1; 1; 1; 1; 1; 1; 1; 1; 1; 1; 1; 1; 1; 1; 1; 1; 1; 1; 1; 1]</factor>
   <delay>[0; 0; 0; 0; 0; 0; 0; 0; 0; 0; 0; 0; 0; 0; 0; 0; 0; 0; 0; 0; 0; 0; 0; 0; 0; 0]</delay>
   <expr>y=sum([x{:}],2)</expr>
</ROOT>